LICENSE
MANIFEST.in
README.md
setup.py
bin/config.json.example
bin/fbd-gather
fbd/__init__.py
fbd/alembic.ini.example
fbd/gatherer.py
fbd/google_api.json.example
fbd/migrate
fbd/storage.py
fbd/tools.py
fbd/visualizer.py
fbd.egg-info/PKG-INFO
fbd.egg-info/SOURCES.txt
fbd.egg-info/dependency_links.txt
fbd.egg-info/not-zip-safe
fbd.egg-info/requires.txt
fbd.egg-info/top_level.txt
fbd/migrations/env.py
fbd/migrations/script.py.mako