Metadata-Version: 1.1
Name: fbd
Version: 0.0.1b29
Summary: Facebook data gatherer and analyzer
Home-page: https://github.com/olety/FBD
Author: Oleksii Kyrylchuk
Author-email: olkyrylchuk@gmail.com
License: MIT
Platform: UNKNOWN
Classifier: Development Status :: 2 - Pre-Alpha
Classifier: License :: OSI Approved :: MIT License
Classifier: Programming Language :: Python :: 3.6
Classifier: Topic :: Other/Nonlisted Topic
